MANIFEST.in
README.rst
setup.py
zcbot_resource_sdk/__init__.py
zcbot_resource_sdk/gwd_fp_queue.py
zcbot_resource_sdk/gwdang.py
zcbot_resource_sdk/gwdang_queue.py
zcbot_resource_sdk/jd.py
zcbot_resource_sdk/jd_queue.py
zcbot_resource_sdk/statistic.py
zcbot_resource_sdk/zdm_queue.py
zcbot_resource_sdk.egg-info/PKG-INFO
zcbot_resource_sdk.egg-info/SOURCES.txt
zcbot_resource_sdk.egg-info/dependency_links.txt
zcbot_resource_sdk.egg-info/requires.txt
zcbot_resource_sdk.egg-info/top_level.txt
zcbot_resource_sdk/common/__init__.py
zcbot_resource_sdk/common/decator.py
zcbot_resource_sdk/common/model.py
zcbot_resource_sdk/common/redis_client.py