Metadata-Version: 2.1
Name: zcbot-resource-sdk
Version: 1.0.22
Summary: zcbot resource sdk for zsodata
Home-page: http://www.zsodata.com
Author: zsodata
Author-email: team@zso.io
License: BSD License
Platform: all
Requires-Python: >=3.8
Requires-Dist: pymongo
